{
  "html": "OSE-AAC.html",
  "css": "OSE-AAC.css",
  "authors": "wesbaker",
  "roll20userid": "194284",
  "patreon": "https://www.patreon.com/wesbaker",
  "preview": "OSE-AAC.png",
  "instructions": "Old School Essentials Official character sheet. For more information see [Necrotic Gnome](https://necroticgnome.com/collections/old-school-essentials).\n\nBased off of Sheershym's Old School Essentials character sheet.",
  "useroptions": [
    {
      "attribute": "armorClassType",
      "displayname": "Armor Class Type",
      "displaytranslationkey": "armor-class-type",
      "type": "select",
      "options": [
        "Ascending Armor Class|aac",
        "Descending Armor Class|dac"
      ],
      "optiontranslationkeys": [
        "ascending-armor-class",
        "descending-armor-class"
      ]
    },
    {
      "attribute": "situationalBonusEnabled",
      "displayname": "Situational Bonus Enabled?",
      "displaytranslationkey": "situational-bonus-enabled",
      "type": "select",
      "options": [
        "Enabled|enabled",
        "Disabled|disabled"
      ],
      "optiontranslationkeys": [
        "enabled",
        "disabled"
      ]
    },
    {
      "attribute": "individualInitiative",
      "displayname": "Individual Initiative?",
      "displaytranslationkey": "individual-initiative",
      "type": "select",
      "default": "disabled",
      "options": [
        "Enabled|enabled",
        "Disabled|disabled"
      ],
      "optiontranslationkeys": [
        "enabled",
        "disabled"
      ]
    }
  ]
}
