{
  "html": "nechronica.html",
  "css": "nechronica.css",
  "authors": "Tateck,Mortaine,Gee-chan",
  "roll20userid": "356257,314,325803",
  "preview": "nechronica.png",
  "instructions": "Nechronica Character Sheet : Auto Dice Roll and Auto check result. Original sheet by Tateck. Oct 2023: Sheet updated by Mortaine and Gee-chan to include translation strings and English translation. 롤20 언어를 한국어로 전환하여 원본 한글 시트를 확인하세요. (Switch your Roll20 language to Korean for original Korean language sheet.)",
  "legacy": true
}