{
"adv-u":"ADVANTAGE",
"norm-u":"NORMAL",
"disadv-u":"DISADVANTAGE",
"public:-u":"PUBLIC",
"to-gm:-u":"TO <span class=\"sheet-togm\">GM</span>",
"npc-options-u":"NPC OPTIONS",
"name-u":"NAME",
"npc-type-u":"NPC TYPE",
"npc-type-place":"Medium fiend, any evil alignment",
"armor-class-u":"ARMOR CLASS",
"type-u":"TYPE",
"npc-armor-place":"scale mail",
"hit-points-u":"HIT POINTS",
"formula-u":"FORMULA",
"speed-u":"SPEED",
"npc-speed-place":"30 ft., fly 60ft.",
"attributes-u":"ATTRIBUTES",
"str-u":"STR",
"dex-u":"DEX",
"con-u":"CON",
"int-u":"INT",
"wis-u":"WIS",
"cha-u":"CHA",
"saves-u":"SAVES",
"skills-u":"SKILLS",
"acrobatics-u":"ACROBATICS",
"animal_handling-u":"ANIMAL HANDLING",
"arcana-u":"ARCANA",
"athletics-u":"ATHLETICS",
"deception-u":"DECEPTION",
"history-u":"HISTORY",
"insight-u":"INSIGHT",
"intimidation-u":"INTIMIDATION",
"investigation-u":"INVESTIGATION",
"medicine-u":"MEDICINE",
"nature-u":"NATURE",
"perception-u":"PERCEPTION",
"performance-u":"PERFORMANCE",
"persuasion-u":"PERSUASION",
"religion-u":"RELIGION",
"sleight_of_hand-u":"SLEIGHT OF HAND",
"stealth-u":"STEALTH",
"survival-u":"SURVIVAL",
"damage-vuln-u":"DAMAGE VULNERABILITIES",
"npc-dmg-vuln-place":"fire",
"damage-res-u":"DAMAGE RESISTANCES",
"npc-dmg-res-place":"cold",
"damage-imm-u":"DAMAGE IMMUNITIES",
"npc-dmg-imm-place":"lighting, thunder",
"cond-imm-u":"CONDITION IMMUNITIES",
"npc-cond-imm-place":"charmed",
"senses-u":"SENSES",
"npc-senses-place":"darkvision 120ft., passive Perception 16",
"langs-u":"LANGUAGES",
"npc-langs-place":"Abyssal, Common, Infernal",
"challenge-u":"CHALLENGE",
"xp-u":"XP",
"token_size-u":"TOKEN SIZE",
"spellcast-npc-u":"SPELLCASTING NPC",
"spell-ability-u":"SPELLCASTING ABILITY",
"none-u":"NONE",
"strength-u":"STRENGTH",
"dexterity-u":"DEXTERITY",
"constitution-u":"CONSTITUTION",
"intelligence-u":"INTELLIGENCE",
"wisdom-u":"WISDOM",
"charisma-u":"CHARISMA",
"glob-atk-mod:-u":"GLOBAL MAGIC ATTACK MODIFIER:",
"magic-caster-lvl:-u":"MAGIC CASTER LEVEL:",
"spell_dc_mod:-u":"SPELL SAVE DC MOD:",
"has-reaction-u":"HAS REACTIONS",
"leg-actions:-u":"LEGENDARY ACTIONS:",
"gen-opts-u":"GENERAL OPTIONS",
"npc-u":"NPC",
"roll-queries:-u":"ROLL QUERIES:",
"always-adv":"Always Roll Advantage",
"adv-toggle":"Advantage Toggle",
"query-adv":"Query Advantage",
"never-adv":"Never Roll Advantage",
"whisp-rolls-gm:-u":"WHISPER ROLLS TO GM:",
"never-whisper-roll":"Never Whisper Rolls",
"toggle-roll-whisper":"Whisper Toggle",
"query-whisper-roll":"Query Whisper",
"always-whisper-roll":"Always Whisper Rolls",
"auto-dmg-roll:-u":"AUTO DAMAGE ROLL:",
"never-dmg":"Don't Auto Roll Damage",
"always-dmg":"Auto Roll Damage &amp; Crit",
"npc-name-in-rolls:-u":"NPC NAME IN ROLLS:",
"show":"Show",
"hide":"Hide",
"add-dex-tiebreaker-u":"ADD DEX TIEBREAKER TO INITIATIVE",
"ac":"Armor Class",
"hp":"Hit Points",
"speed":"Speed",
"saving-throw":"Saving Throws",
"str":"Str",
"dex":"Dex",
"con":"Con",
"int":"Int",
"wis":"Wis",
"cha":"Cha",
"skills":"Skills",
"acrobatics":"Acrobatics",
"animal_handling":"Animal Handling",
"arcana":"Arcana",
"athletics":"Athletics",
"deception":"Deception",
"history":"History",
"insight":"Insight",
"intimidation":"Intimidation",
"investigation":"Investigation",
"medicine":"Medicine",
"nature":"Nature",
"perception":"Perception",
"performance":"Performance",
"persuasion":"Persuasion",
"religion":"Religion",
"sleight_of_hand":"Sleight of Hand",
"stealth":"Stealth",
"survival":"Survival",
"dmg-vuln":"Damage Vulnerabilities",
"dmg-res":"Damage Resistances",
"dmg-imm":"Damage Immunities",
"cond-imm":"Condition Immunities",
"senses":"Senses",
"langs":"Languages",
"challenge":"Challenge",
"npc-trait-name-place":"False Appearance.",
"npc-trait-desc-place":"If the dragon fails...",
"actions":"Actions",
"name:-u":"NAME:",
"attack-u":"ATTACK",
"type:-u":"TYPE:",
"melee":"Melee",
"ranged":"Ranged",
"range-reach:-u":"RANGE/REACH:",
"range-reach-place":"5 ft.",
"to-hit:-u":"TO HIT:",
"target:-u":"TARGET:",
"to-hit-place":"One target",
"on-hit:-u":"ON HIT:",
"on-hit-place":"slashing",
"on-hit2:-u":"ON HIT 2:",
"on-hit-2-place":"fire",
"desc:-u":"DESCRIPTION:",
"hit:":"Hit: ",
"reactions":"Reactions",
"npc-repeating-name-place":"Parry.",
"npc-repeating-desc-place":"The creature adds 2 to its AC against...",
"leg-actions":"Legendary Actions",
"leg-actions-desc":"<span name=\"attr_npc_legendary_actions_desc\"></span>",
"spells":"Spells",
"school:-u":"SCHOOL:",
"abjuration":"Abjuration",
"conjuration":"Conjuration",
"divination":"Divination",
"enchantment":"Enchantment",
"evocation":"Evocation",
"illusion":"Illusion",
"necromancy":"Necromancy",
"transmutation":"Transmutation",
"ritual-u":"RITUAL",
"casting-time:-u":"CASTING TIME:",
"range:-u":"RANGE:",
"components:-u":"COMPONENTS:",
"spell-component-verbal":"V",
"spell-component-somatic":"S",
"spell-component-material":"M",
"ruby-dust-place":"ruby dust worth 50gp",
"concentration-u":"CONCENTRATION",
"duration:-u":"DURATION:",
"innate:-u":"INNATE:",
"output:-u":"OUTPUT:",
"spellcard-u":"SPELLCARD",
"spell-atk:-u":"SPELL ATTACK:",
"none":"None",
"dmg:-u":"DAMAGE:",
"dmg2:-u":"DAMAGE2:",
"healing:-u":"HEALING:",
"add-ability-mod-u":"ADD ABILITY MOD TO DAMAGE OR HEALING",
"saving-throw:-u":"SAVING THROW:",
"effect:-u":"EFFECT:",
"npc-atk-effect-place":"Half damage",
"at-higher-lvl-dmg:-u":"HIGHER LVL CAST DMG:",
"include_spell_desc:-u":"INCLUDE SPELL DESCRIPTION IN ATTACK:",
"on":"On",
"off":"Off",
"at-higher-lvl:-u":"AT HIGHER LEVELS:",
"core-u":"CORE",
"bio-u":"BIO",
"spells-u":"SPELLS",
"char-name-u":"CHARACTER NAME",
"class:-u":"CLASS:",
"choose":"Choose",
"barbarian":"Barbarian",
"bard":"Bard",
"cleric":"Cleric",
"druid":"Druid",
"fighter":"Fighter",
"monk":"Monk",
"paladin":"Paladin",
"ranger":"Ranger",
"rogue":"Rogue",
"sorcerer":"Sorcerer",
"warlock":"Warlock",
"wizard":"Wizard",
"subclass:-u":"SUBCLASS:",
"lvl:-u":"LEVEL:",
"race:-u":"RACE:",
"subrace:-u":"SUBRACE:",
"class-level-u":"CLASS &amp; LEVEL",
"background-u":"BACKGROUND",
"race-u":"RACE",
"alignment-u":"ALIGNMENT",
"exp-pts-u":"EXPERIENCE POINTS",
"inspiration-u":"INSPIRATION",
"prof-bonus-u":"PROFICIENCY BONUS",
"strength":"Strength",
"dexterity":"Dexterity",
"constitution":"Constitution",
"intelligence":"Intelligence",
"wisdom":"Wisdom",
"charisma":"Charisma",
"global-save-u":"GLOBAL SAVE MODIFIER",
"roll:-u":"ROLL:",
"saving-throws-u":"SAVING THROWS",
"acrobatics-core":"Acrobatics <span>(Dex)</span>",
"animal_handling-core":"Animal Handling <span>(Wis)</span>",
"arcana-core":"Arcana <span>(Int)</span>",
"athletics-core":"Athletics <span>(Str)</span>",
"deception-core":"Deception <span>(Cha)</span>",
"history-core":"History <span>(Int)</span>",
"insight-core":"Insight <span>(Wis)</span>",
"intimidation-core":"Intimidation <span>(Cha)</span>",
"investigation-core":"Investigation <span>(Int)</span>",
"medicine-core":"Medicine <span>(Wis)</span>",
"nature-core":"Nature <span>(Int)</span>",
"perception-core":"Perception <span>(Wis)</span>",
"performance-core":"Performance <span>(Cha)</span>",
"persuasion-core":"Persuasion <span>(Cha)</span>",
"religion-core":"Religion <span>(Int)</span>",
"sleight_of_hand-core":"Sleight of Hand <span>(Dex)</span>",
"stealth-core":"Stealth <span>(Dex)</span>",
"survival-core":"Survival <span>(Wis)</span>",
"pass-wis-u":"PASSIVE WISDOM (PERCEPTION)",
"tool-u":"TOOL",
"pro-u":"PRO",
"attr-u":"ATTRIBUTE",
"prof-bonus:-u":"PROFICIENCY BONUS:",
"prof-u":"PROFICIENT",
"expertise-u":"EXPERTISE",
"jack-of-all-u":"JACK OF ALL TRADES",
"attr:-u":"ATTRIBUTE:",
"query-attr-u":"QUERY ATTRIBUTE",
"mods:-u":"MODS:",
"global-skill-u":"GLOBAL SKILL MODIFIER",
"tool-prof-u":"TOOL PROFICIENCIES",
"custom-skills-u":"CUSTOM SKILLS",
"proficency-u":"PROFICIENCY",
"lang-u":"LANGUAGE",
"weapon-u":"WEAPON",
"armor-u":"ARMOR",
"other-u":"OTHER",
"other-prof-langs-u":"OTHER PROFICIENCIES &amp; LANGUAGES",
"init-u":"INITIATIVE",
"hp-max-u":"Hit Point Maximum",
"hp-current-u":"CURRENT HIT POINTS",
"hp-temp-u":"TEMPORARY HIT POINTS",
"total":"Total",
"hit-dice-u":"HIT DICE",
"successes-u":"SUCCESSES",
"failures-u":"FAILURES",
"death-saves-u":"DEATH SAVES",
"exhaustion-u":"EXHAUSTION LEVEL",
"atk-u":"ATK",
"dmg-type-u":"DAMAGE/TYPE",
"attack:-u":"ATTACK:",
"spell-u":"SPELL",
"proficient-u":"PROFICIENT",
"range-place":"Self (60-foot cone)",
"magic-bonus:-u":"MAGIC BONUS:",
"crit-range-u":"CRIT RANGE:",
"damage:-u":"DAMAGE:",
"dmg-type-place":"Slashing",
"crit:-u":"CRIT:",
"damage2:-u":"DAMAGE2:",
"vs-dc:-u":"VS DC:",
"flat-u":"FLAT",
"save-effect:-u":"SAVE EFFECT:",
"save-effect-place":"half damage",
"ammunition:-u":"AMMUNITION:",
"ammunition-place":"Arrows",
"description:-u":"DESCRIPTION:",
"description-place":"Up to 2 creatures within 5 feet",
"global-attack-u":"GLOBAL ATTACK MODIFIER",
"global-damage-u":"GLOBAL DAMAGE MODIFIER",
"atk-spellcasting-u":"ATTACKS &amp; SPELLCASTING",
"global-ac-u":"GLOBAL AC MODIFIER",
"copper-piece-u":"CP",
"silver-piece-u":"SP",
"electrum-piece-u":"EP",
"gold-piece-u":"GP",
"platinum-piece-u":"PP",
"warning-armor-sets-u":"\n                                WARNING - MULTIPLE SETS OF ARMOR OR SHIELDS HAVE BEEN ADDED AND AC IS NOT CORRECTLY CALCULATED. UNEQUIP THE ARMOR PIECE FROM THE ITEM DETAILS.n                            ",
"warning-customac-u":"\n                                ATTENTION - YOUR CUSTOM AC CALCULATION IS NOT BEING USED AS YOU HAVE ARMOR EQUIPPED. IF YOU WANT TO USE YOUR CUSTOM AC, UNEQUIP THE ARMOR PIECE FROM THE ITEM DETAILS.n                            ",
"item-name-u":"ITEM NAME",
"equipped-u":"EQUIPPED",
"use-as-resource-u":"USE AS A RESOURCE",
"has-attack-u":"HAS AN ATTACK",
"prop:-u":"PROP:",
"total-weight-u":"TOTAL WEIGHT",
"immobile-u":"IMMOBILE",
"heavily-encumbered-u":"HEAVILY ENCUMBERED",
"encumbered-u":"ENCUMBERED",
"over-carrying-cap-u":"OVER CARRYING CAPACITY",
"equipment-u":"EQUIPMENT",
"personality-traits-u":"PERSONALITY TRAITS",
"ideals-u":"IDEALS",
"bonds-u":"BONDS",
"flaws-u":"FLAWS",
"class-resource-u":"CLASS RESOURCE",
"other-resource-u":"OTHER RESOURCE",
"source:-u":"SOURCE:",
"racial":"Racial",
"class":"Class",
"feat":"Feat",
"background":"Background",
"other":"Other",
"source-type:-u":"SOURCE TYPE:",
"feats-traits-u":"FEATURES AND TRAITS",
"age-u":"AGE",
"size-u":"SIZE",
"height-u":"HEIGHT",
"weight-u":"WEIGHT",
"eye-u":"EYES",
"skin-u":"SKIN",
"hair-u":"HAIR",
"char-appearance-u":"CHARACTER APPEARANCE",
"char-backstory-u":"CHARACTER BACKSTORY",
"allies-orgs-u":"ALLIES &amp; ORGANIZATIONS",
"add-feats-traits-u":"ADDITIONAL FEATURES &amp; TRAITS",
"treasure-u":"TREASURE",
"spell-save-dc-u":"SPELL SAVE DC",
"spell-atk-bonus-u":"SPELL ATTACK BONUS",
"cantrips-u":"CANTRIPS",
"cantrip-progression:-u":"CANTRIP PROGRESSION",
"cantrip-dice-u":"CANTRIP DICE",
"cantrip-beam-u":"CANTRIP BEAM",
"half-dmg-place":"Half damage",
"partial":"Partial",
"spell-ritual":"R",
"spell-concentration":"C",
"slots_total-u":"SLOTS TOTAL",
"slots_remaining-u":"SLOTS REMAINING",
"hit-die:-u":"HIT DIE:",
"carrying-capacity-mod:-u":"CARRYING CAPACITY MODIFIER:",
"spell-icons:-u":"SPELL ICONS:",
"show_all":"Show All",
"cr_only":"C&amp;R Only",
"halfling-luck-u":"HALFLING LUCK",
"arcane-fighter-u":"ARCANE FIGHTER",
"arcane-rogue-u":"ARCANE ROGUE",
"class-options-u":"CLASS OPTIONS (<span name=\"attr_class\" data-i18n-dynamic=\"\"></span>)",
"2nd-class:-u":"2ND CLASS:",
"3rd-class:-u":"3RD CLASS:",
"4th-class:-u":"4TH CLASS:",
"mutliclass-opts-u":"MULTICLASS OPTIONS",
"use-cust-class-u":"USE CUSTOM CLASS",
"class-name:-u":"CLASS NAME:",
"spellcasting-ability:-u":"SPELLCASTING ABILITY:",
"spell-slots:-u":"SPELL SLOTS:",
"spell-full-u":"FULL (Cleric, Druid, Wizard)",
"spell-half-u":"HALF (Paladin, Ranger)",
"spell-third-u":"THIRD (Arcane Fighter/Rogue)",
"cust-class-opts":"CUSTOM CLASS OPTIONS",
"lvl-u":"LEVEL",
"spell_slot_modifiers-u":"SPELL SLOT MODIFIERS",
"initiative-mod:-u":"INITIATIVE MODIFIER:",
"initiative-style:-u":"INITIATIVE STYLE:",
"norm":"Normal",
"adv":"Advantage",
"disadv":"Disadvantage",
"armor-class-tracking:-u":"ARMOR CLASS TRACKING:",
"automatic":"Automatic",
"custom":"Custom",
"custom_ac:-u":"CUSTOM AC:",
"allow-shields-u":"ALLOW SHIELDS?",
"hpmods:-u":"HP MODIFIERS:",
"levels:-u":"LEVELS:",
"total-level-u":"TOTAL LEVEL",
"main-class-level-u":"MAIN CLASS LEVEL",
"class-2-level-u":"CLASS 2 LEVEL",
"class-3-level-u":"CLASS 3 LEVEL",
"class-4-level-u":"CLASS 4 LEVEL",
"mod:-u":"MOD:",
"attribute-opts-u":"ATTRIBUTE OPTIONS",
"strength-save-u":"Strength Save",
"dexterity-save-u":"Dexterity Save",
"constitution-save-u":"Constitution Save",
"intelligence-save-u":"Intelligence Save",
"wisdom-save-u":"Wisdom Save",
"charisma-save-u":"Charisma Save",
"death-save-mod:-u":"DEATH SAVE MODIFIER:",
"glob-saving-mod:-u":"GLOBAL SAVING THROW MODIFIER:",
"save-opts-u":"SAVE OPTIONS",
"normal":"Normal",
"expirtise":"Expertise",
"pass-perc-mod:-u":"PASSIVE PERCEPTION MODIFIER:",
"skill-opts-u":"SKILL OPTIONS",
"version":"v",
"always-roll-adv":"Always Roll Advantage",
"toggle-roll-adv":"Advantage Toggle",
"query-roll-adv":"Query Advantage",
"never-roll-adv":"Never Roll Advantage",
"never-roll-dmg":"Don't Auto Roll Damage",
"always-roll-dmg":"Auto Roll Damage &amp; Crit",
"core-die-roll:-u":"CORE DIE ROLL:",
"by-level":"By Level (Default)",
"prof-die":"Proficency Die (DMG)",
"show-global-save-field-u":"SHOW GLOBAL SAVE MODIFIER FIELD",
"show-global-skill-field-u":"SHOW GLOBAL SKILL MODIFIER FIELD",
"show-global-attack-field-u":"SHOW GLOBAL ATTACK MODIFIER FIELD",
"show-global-damage-field-u":"SHOW GLOBAL DAMAGE MODIFIER FIELD",
"show-global-ac-field-u":"SHOW GLOBAL AC MODIFIER FIELD",
"add-char-to-templates:-u":"ADD CHARACTER NAME TO TEMPLATES:",
"level-calculations:-u":"LEVEL CALCULATIONS:",
"encumbrance:-u":"ENCUMBRANCE:",
"simple":"Simple",
"variant-phb":"Variant (PHB p176)",
"inventory:-u":"INVENTORY:",
"compendium-compatible":"Compendium Compatible",
"prof-langs-u":"PROFICENCIES AND LANGUAGES",
"ammo-tracking:-u":"AMMO TRACKING:",
"api-required-title":"Try it now with easy one click API installation available with your Pro subscription.",
"api-required-u":"(API REQUIRED)",
"exhaustion-setting-u":"SHOW EXHAUSTION TRACKING:",
"general-opts-u":"GENERAL OPTIONS",
"warning-leveler_start-u":"\n                            ATTENTION - YOU CANNOT LAUNCH THE CHARACTERMANCER LEVEL UP UNTIL YOU HAVE A CLASS, LEVEL, AND HP SET FOR LEVEL ONE. PLEASE RUN THE CHARACTERMANCER CREATOR FIRST. THE LEVEL UP TOOL DOESN'T WORK WITH CUSTOM CLASSES OR IF THE MULTICLASS OPTIONS ARE SET UP INCORRECTLY.n                        ",
"relaunch-lvl1mancer-u":"LAUNCH LEVEL 1 CHARACTERMANCER (CANNOT BE UNDONE)",
"mancer-opts-u":"CHARACTERMANCER OPTIONS",
"portions-sheet-utilize":"\n            Portions of this sheet utilize content from the System Reference Document 5.0 under the OGL License. View OGL License and Copyright Notice. https://wiki.roll20.net/SRD_5.0_OGL_Licensen        ",
"footer-wiki-link":"\n            For more information about this character sheet, its functionality, or uses, please check out the Roll20 Wiki for official documentation. https://wiki.roll20.net/5th_Edition_OGL_by_Roll20n        ",
"accepting-drop-u":"ACCEPTING DROP FROM COMPENDIUM",
"are_you_sure":"Are you sure you want to turn this character into a ",
"yes":"Yes",
"cancel":"Cancel",
"do_you_want_mancer":"How do  you want to create this character?",
"mancer-confirm-yes":"Use the Charactermancer",
"npc-new":"Create an NPC",
"manual":"Edit sheet direclty"
}
