{
  "name": "D6++ Modern",
  "format": "legacy",
  "html": "d6ppmodern.html",
  "css": "d6ppmodern.css",
  "authors": "MmpApps Corp.",
  "roll20userid": "10156180",
  "instructions": "Designed for the D6++ Modern RPG system.",
  "version": 1,
  "description": "Compatible with the D6++ Modern RPG system. Designed for fast-paced cinematic gameplay, this sheet is fully integrated with the D6++ Modern Compendium.\n\n- Drag-and-drop ready for weapons, items, and gear from the Compendium.\n- Streamlined layout optimized for clarity and speed during play.\n- Auto-calculations for skills, wounds, and modifiers to keep the action flowing.\n- Pre-built roll buttons for all major actions—just click and play.\n- Training mode and background selection built directly into the sheet.\n- Customizable attributes, weapons, and gear for player characters, and NPCs.\n- Supports all official D6++ mechanics including conditions, reactions, and declared actions.\n- Flexible sheet types: Player Character, Vehicles, Beasts, Major NPC, Standard NPC, and Quick NPC",
  "compendium": "d6pp-modern",
  "preview": "d6ppmodern.png"
}
