{
  "html": "RogueTraderImproved.html",
  "css": "RogueTraderImproved.css",
  "authors": "Mago",
  "roll20userid": "986445",
  "preview": "RTimprovedPreview.png",
  "instructions": "<p>Character Sheet designed to play Warhammer 40k Rogue Trader pen & paper RPG by Fantasy Flight Games.\nThis Sheet does Not require API scripts.</p><p>Check out this sheet Wiki page for more information about all of its features at [Rogue Trader Improved Wiki](https://wiki.roll20.net/Rogue_trader_improved)</p><p>**IMPORTANT TIP** The roll template is best displayed in chat when **turning off the ENABLE CHAT AVATARS** option in the My Settings tab.</p><p>If you have any questions, suggestions or feedback, send a private message to [Mago](https://app.roll20.net/users/986445/mago)</p><p>**Revision 4 June 2024**</p>",
  "legacy": false
}