{
  "html": "imsheet.html",
  "css": "imsheet.css",
  "authors": "Craig Garrett (@clgarret)",
  "roll20userid": "561389",
  "preview": "imsheet1.png",
  "instructions": "Sheet for the Imperium Maledictum RPG.  Includes Character, Combat, and Patron pages.  You can roll Characteristics and Skills by pressing the labels.  You can roll Specialisations, Weapons, and Psychic Powers by pressing the [*] button beside the name.  Rolls include advantage, superiority, difficulty, plus an extra modifier if needed.  You can contact Craig G if you have any questions.  Enjoy.",
  "legacy": false
}